{
  "interactionModel": {
    "languageModel": {
      "invocationName": "nabu",
      "intents": [
        {
          "name": "AskAssistIntent",
          "slots": [
            {
              "name": "query",
              "type": "AMAZON.SearchQuery"
            }
          ],
          "samples": [
            "tell me {query}",
            "ask {query}",
            "please {query}",
            "can you {query}",
            "could you {query}",
            "i want to know {query}"
          ]
        },
        {
          "name": "AskAssistWhatIntent",
          "slots": [
            {
              "name": "query",
              "type": "AMAZON.SearchQuery"
            }
          ],
          "samples": [
            "what {query}"
          ]
        },
        {
          "name": "AskAssistWhyIntent",
          "slots": [
            {
              "name": "query",
              "type": "AMAZON.SearchQuery"
            }
          ],
          "samples": [
            "why {query}"
          ]
        },
        {
          "name": "AskAssistHowIntent",
          "slots": [
            {
              "name": "query",
              "type": "AMAZON.SearchQuery"
            }
          ],
          "samples": [
            "how {query}"
          ]
        },
        {
          "name": "AskAssistWhereIntent",
          "slots": [
            {
              "name": "query",
              "type": "AMAZON.SearchQuery"
            }
          ],
          "samples": [
            "where {query}"
          ]
        },
        {
          "name": "AskAssistWhenIntent",
          "slots": [
            {
              "name": "query",
              "type": "AMAZON.SearchQuery"
            }
          ],
          "samples": [
            "when {query}"
          ]
        },
        {
          "name": "AskAssistIsIntent",
          "slots": [
            {
              "name": "query",
              "type": "AMAZON.SearchQuery"
            }
          ],
          "samples": [
            "is {query}"
          ]
        },
        {
          "name": "AskAssistAreIntent",
          "slots": [
            {
              "name": "query",
              "type": "AMAZON.SearchQuery"
            }
          ],
          "samples": [
            "are {query}"
          ]
        },
        {
          "name": "AskAssistTurnIntent",
          "slots": [
            {
              "name": "query",
              "type": "AMAZON.SearchQuery"
            }
          ],
          "samples": [
            "turn {query}"
          ]
        },
        {
          "name": "AskAssistSetIntent",
          "slots": [
            {
              "name": "query",
              "type": "AMAZON.SearchQuery"
            }
          ],
          "samples": [
            "set {query}"
          ]
        },
        {
          "name": "AskAssistOpenIntent",
          "slots": [
            {
              "name": "query",
              "type": "AMAZON.SearchQuery"
            }
          ],
          "samples": [
            "open {query}"
          ]
        },
        {
          "name": "AskAssistCloseIntent",
          "slots": [
            {
              "name": "query",
              "type": "AMAZON.SearchQuery"
            }
          ],
          "samples": [
            "close {query}"
          ]
        },
        {
          "name": "AMAZON.HelpIntent",
          "samples": []
        },
        {
          "name": "AMAZON.CancelIntent",
          "samples": []
        },
        {
          "name": "AMAZON.StopIntent",
          "samples": []
        },
        {
          "name": "AMAZON.FallbackIntent",
          "samples": []
        }
      ],
      "types": []
    }
  }
}
